MANIFEST.in
README.md
setup.py
pypesq/__init__.py
pypesq/dsp.c
pypesq/dsp.h
pypesq/pesq.c
pypesq/pesq.h
pypesq/pesqdsp.c
pypesq/pesqio.c
pypesq/pesqmain.c
pypesq/pesqmod.c
pypesq/pesqpar.h
pypesq.egg-info/PKG-INFO
pypesq.egg-info/SOURCES.txt
pypesq.egg-info/dependency_links.txt
pypesq.egg-info/not-zip-safe
pypesq.egg-info/requires.txt
pypesq.egg-info/top_level.txt